lynx_flow/__init__.py
lynx_flow/lynx.py
lynx_flow-0.0.3.dist-info/LICENSE
lynx_flow-0.0.3.dist-info/METADATA
lynx_flow-0.0.3.dist-info/WHEEL
lynx_flow-0.0.3.dist-info/top_level.txt
lynx_flow-0.0.3.dist-info/RECORD
