Metadata-Version: 2.1
Name: lynx-flow
Version: 0.0.3
Summary: Lynx Flow is a streamlined and straightforward API requests library for building method call sequences. Simplify your code with clear and concise constructs using Lynx Flow.
Author: Toghrul Mirzayev
Author-email: togrul.mirzoev@gmail.com
Keywords: testing,api,rest,graphql,backend,qa,test-automation,automation
Classifier: Development Status :: 2 - Pre-Alpha
Classifier: Intended Audience :: Developers
Classifier: License :: OSI Approved :: MIT License
Classifier: Programming Language :: Python :: 3
Classifier: Programming Language :: Python :: 3.7
Classifier: Programming Language :: Python :: 3.8
Classifier: Programming Language :: Python :: 3.9
Classifier: Topic :: Software Development :: Testing
Requires-Python: >=3.7
License-File: LICENSE
Requires-Dist: requests
Requires-Dist: logstyle
